agent_observability/__init__.py
agent_observability/client.py
agent_observability/env_loader.py
agent_observability/exceptions.py
agent_observability/models.py
agent_observability-1.5.0.dist-info/METADATA
agent_observability-1.5.0.dist-info/WHEEL
agent_observability-1.5.0.dist-info/top_level.txt
agent_observability-1.5.0.dist-info/RECORD
