Metadata-Version: 2.4
Name: agent-observability
Version: 1.5.0
Summary: Agent observability with cost tracking and compliance audit trails
Home-page: https://github.com/blueskylineassets/agent-observability
Author: Agent Observability Team
Author-email: Agent Observability Team <support@agentobs.io>
License: MIT
Project-URL: Homepage, https://github.com/blueskylineassets/agent-observability
Project-URL: Documentation, https://blueskylineassets.github.io/agent-observability/dashboard/getting-started.html
Project-URL: Pricing, https://blueskylineassets.github.io/agent-observability/dashboard/pricing.html
Project-URL: API, https://api-production-0c55.up.railway.app
Keywords: agent,observability,logging,compliance,audit,ai-agent,langchain,autogpt,crewai
Classifier: Development Status :: 4 - Beta
Classifier: Intended Audience :: Developers
Classifier: License :: OSI Approved :: MIT License
Classifier: Programming Language :: Python :: 3.10
Classifier: Programming Language :: Python :: 3.11
Classifier: Programming Language :: Python :: 3.12
Classifier: Topic :: Software Development :: Libraries
Classifier: Topic :: System :: Monitoring
Requires-Python: >=3.9
Requires-Dist: httpx>=0.25.0
Provides-Extra: dev
Requires-Dist: pytest>=8.0.0; extra == "dev"
Requires-Dist: pytest-asyncio>=0.23.0; extra == "dev"
Requires-Dist: black>=24.0.0; extra == "dev"
Requires-Dist: mypy>=1.8.0; extra == "dev"
Dynamic: author
Dynamic: home-page
Dynamic: requires-python
